cdf/__init__.py
cdf/domain/__init__.py
cdf/domain/latest/__init__.py
cdf/domain/latest/event.py
cdf/domain/latest/match.py
cdf/domain/latest/meta.py
cdf/domain/latest/skeletal.py
cdf/domain/latest/tracking.py
cdf/domain/latest/video.py
cdf/files/sample/event_v0.2.0.jsonl
cdf/files/sample/match_v0.2.0.json
cdf/files/sample/meta_v0.2.0.json
cdf/files/sample/skeletal_v0.2.0.jsonl
cdf/files/sample/tracking_v0.2.0.jsonl
cdf/files/sample/video_v0.2.0.json
cdf/files/schema/event_v0.2.0.json
cdf/files/schema/match_v0.2.0.json
cdf/files/schema/meta_v0.2.0.json
cdf/files/schema/skeletal_v0.2.0.json
cdf/files/schema/tracking_v0.2.0.json
cdf/files/schema/video_v0.2.0.json
cdf/files/v0.2.0/sample/event.jsonl
cdf/files/v0.2.0/sample/match.json
cdf/files/v0.2.0/sample/meta.json
cdf/files/v0.2.0/sample/skeletal.jsonl
cdf/files/v0.2.0/sample/tracking.jsonl
cdf/files/v0.2.0/sample/video.json
cdf/files/v0.2.0/schema/event.json
cdf/files/v0.2.0/schema/match.json
cdf/files/v0.2.0/schema/meta.json
cdf/files/v0.2.0/schema/skeletal.json
cdf/files/v0.2.0/schema/tracking.json
cdf/files/v0.2.0/schema/video.json
cdf/files/v0.2.1/sample/event.jsonl
cdf/files/v0.2.1/sample/match.json
cdf/files/v0.2.1/sample/meta.json
cdf/files/v0.2.1/sample/skeletal.jsonl
cdf/files/v0.2.1/sample/tracking.jsonl
cdf/files/v0.2.1/sample/video.json
cdf/files/v0.2.1/schema/event.json
cdf/files/v0.2.1/schema/match.json
cdf/files/v0.2.1/schema/meta.json
cdf/files/v0.2.1/schema/skeletal.json
cdf/files/v0.2.1/schema/tracking.json
cdf/files/v0.2.1/schema/video.json
cdf/files/v0.2.2/sample/event.jsonl
cdf/files/v0.2.2/sample/match.json
cdf/files/v0.2.2/sample/meta.json
cdf/files/v0.2.2/sample/skeletal.jsonl
cdf/files/v0.2.2/sample/tracking.jsonl
cdf/files/v0.2.2/sample/video.json
cdf/files/v0.2.2/schema/event.json
cdf/files/v0.2.2/schema/match.json
cdf/files/v0.2.2/schema/meta.json
cdf/files/v0.2.2/schema/skeletal.json
cdf/files/v0.2.2/schema/tracking.json
cdf/files/v0.2.2/schema/video.json
cdf/validators/__init__.py
common_data_format_validator-0.0.13.dist-info/LICENSE.md
common_data_format_validator-0.0.13.dist-info/METADATA
common_data_format_validator-0.0.13.dist-info/WHEEL
common_data_format_validator-0.0.13.dist-info/top_level.txt
common_data_format_validator-0.0.13.dist-info/RECORD
