Metadata-Version: 2.1
Name: common-data-format-validator
Version: 0.0.13
Summary: A package for validating common data format files
Home-page: https://github.com/unravelsports/common-data-format-validator
Author: Joris Bekkers
Author-email: joris@pysport.org
Classifier: Programming Language :: Python :: 3
Classifier: Operating System :: OS Independent
Requires-Python: >=3.9
License-File: LICENSE.md
Requires-Dist: jsonlines==4.0.0
Requires-Dist: jsonschema==4.23.0
Requires-Dist: jsonschema-specifications==2024.10.1
Requires-Dist: requests==2.32.3
Provides-Extra: dev
Requires-Dist: json-schema-for-humans>=1.4.1; extra == "dev"
Requires-Dist: pytest>=8.4.0; extra == "dev"
